README.rst
option_merge_addons.py
setup.py
option_merge_addons.egg-info/PKG-INFO
option_merge_addons.egg-info/SOURCES.txt
option_merge_addons.egg-info/dependency_links.txt
option_merge_addons.egg-info/requires.txt
option_merge_addons.egg-info/top_level.txt