Metadata-Version: 2.1
Name: option-merge-addons
Version: 0.3
Summary: Addons for option_merge
Home-page: http://github.com/delfick/option_merge_addons
Author: Stephen Moore
Author-email: delfick755@gmail.com
License: WTFPL
Platform: UNKNOWN
Provides-Extra: tests
